mcazurerm
