Metadata-Version: 1.0
Name: mcazurerm
Version: 0.1.1
Summary: Azure Resource Manager REST wrappers
Home-page: http://github.com/pjshi23/mcazurerm
Author: Stan Peng
Author-email: pjshi23@gmail.com
License: MIT
Platform: UNKNOWN
